pyjuice/__init__.py
pyjuice/distributions/__init__.py
pyjuice/graph/__init__.py
pyjuice/graph/region_graph.py
pyjuice/io/__init__.py
pyjuice/io/io.py
pyjuice/io/serialization.py
pyjuice/layer/__init__.py
pyjuice/layer/compilation.py
pyjuice/layer/input_layer.py
pyjuice/layer/layer.py
pyjuice/layer/layer_group.py
pyjuice/layer/prod_layer.py
pyjuice/layer/sum_layer.py
pyjuice/layer/backend/__init__.py
pyjuice/layer/backend/index_set.py
pyjuice/layer/backend/node_partition.py
pyjuice/model/__init__.py
pyjuice/model/tensorcircuit.py
pyjuice/model/backend/__init__.py
pyjuice/model/backend/eval_partition.py
pyjuice/model/backend/normalize.py
pyjuice/model/backend/par_update.py
pyjuice/model/backend/parflow_fusing.py
pyjuice/model/backend/top_down_prob.py
pyjuice/nodes/__init__.py
pyjuice/nodes/construction.py
pyjuice/nodes/input_nodes.py
pyjuice/nodes/nodes.py
pyjuice/nodes/prod_nodes.py
pyjuice/nodes/sum_nodes.py
pyjuice/nodes/backend/__init__.py
pyjuice/nodes/backend/normalize.py
pyjuice/nodes/distributions/__init__.py
pyjuice/nodes/distributions/bernoulli.py
pyjuice/nodes/distributions/categorical.py
pyjuice/nodes/distributions/discrete_logistic.py
pyjuice/nodes/distributions/distributions.py
pyjuice/nodes/distributions/external.py
pyjuice/nodes/distributions/external_categorical.py
pyjuice/nodes/distributions/gaussian.py
pyjuice/nodes/distributions/literal.py
pyjuice/nodes/distributions/masked_categorical.py
pyjuice/nodes/methods/__init__.py
pyjuice/nodes/methods/edge_constructors.py
pyjuice/nodes/methods/lvd.py
pyjuice/nodes/methods/scope.py
pyjuice/nodes/methods/traversal.py
pyjuice/nodes/methods/lvd_backend/__init__.py
pyjuice/nodes/methods/lvd_backend/counting.py
pyjuice/optim/__init__.py
pyjuice/optim/optim.py
pyjuice/optim/scheduler.py
pyjuice/queries/__init__.py
pyjuice/queries/base.py
pyjuice/queries/conditional.py
pyjuice/queries/marginal.py
pyjuice/queries/sample.py
pyjuice/structures/__init__.py
pyjuice/structures/compilation.py
pyjuice/structures/hclt.py
pyjuice-2.4.1.dist-info/licenses/LICENSE
pyjuice-2.4.1.dist-info/METADATA
pyjuice-2.4.1.dist-info/WHEEL
pyjuice-2.4.1.dist-info/top_level.txt
pyjuice-2.4.1.dist-info/RECORD
