Metadata-Version: 2.4
Name: pyjuice
Version: 2.4.1
Summary: Probabilistic Circuits Library
Author-email: Anji Liu <anjiliu@comp.nus.edu.sg>, StarAI <guyvdb@cs.ucla.edu>
License-File: LICENSE
Requires-Dist: numpy
Requires-Dist: torch>=2.2.0
Requires-Dist: typing
Requires-Dist: triton>=2.2.0
Requires-Dist: networkx
Requires-Dist: numba
Requires-Dist: packaging
Requires-Dist: matplotlib
Requires-Dist: tqdm
Provides-Extra: dev
Requires-Dist: pytest; extra == "dev"
Requires-Dist: pytest-xdist; extra == "dev"
Requires-Dist: pytest-skip-slow; extra == "dev"
Requires-Dist: torchvision; extra == "dev"
Requires-Dist: datasets; extra == "dev"
Requires-Dist: matplotlib; extra == "dev"
Dynamic: license-file
